odoo9_addon_purchase_delivery_split_date-9.0.1.0.0-py2.7-nspkg.pth
odoo9_addon_purchase_delivery_split_date-9.0.1.0.0.dist-info/top_level.txt
odoo9_addon_purchase_delivery_split_date-9.0.1.0.0.dist-info/WHEEL
odoo9_addon_purchase_delivery_split_date-9.0.1.0.0.dist-info/RECORD
odoo9_addon_purchase_delivery_split_date-9.0.1.0.0.dist-info/metadata.json
odoo9_addon_purchase_delivery_split_date-9.0.1.0.0.dist-info/DESCRIPTION.rst
odoo9_addon_purchase_delivery_split_date-9.0.1.0.0.dist-info/METADATA
odoo9_addon_purchase_delivery_split_date-9.0.1.0.0.dist-info/namespace_packages.txt
odoo_addons/purchase_delivery_split_date/__openerp__.py
odoo_addons/purchase_delivery_split_date/__init__.py
odoo_addons/purchase_delivery_split_date/README.rst
odoo_addons/purchase_delivery_split_date/models/purchase.py
odoo_addons/purchase_delivery_split_date/models/__init__.py
odoo_addons/purchase_delivery_split_date/i18n/it.po
odoo_addons/purchase_delivery_split_date/i18n/es.po
odoo_addons/purchase_delivery_split_date/i18n/sl.po
odoo_addons/purchase_delivery_split_date/i18n/de.po
odoo_addons/purchase_delivery_split_date/i18n/fr.po
odoo_addons/purchase_delivery_split_date/i18n/pt_BR.po
odoo_addons/purchase_delivery_split_date/tests/__init__.py
odoo_addons/purchase_delivery_split_date/tests/test_purchase_delivery.py
